{
  "animateLoading": true,
  "borderRadius": "{{appsmith.theme.borderRadius.appBorderRadius}}",
  "bottomRow": 12,
  "displayName": "Text",
  "dynamicBindingPathList": [
    {
      "key": "truncateButtonColor"
    },
    {
      "key": "borderRadius"
    }
  ],
  "dynamicHeight": "AUTO_HEIGHT",
  "dynamicTriggerPathList": [],
  "fontFamily": "System Default",
  "fontSize": "0.875rem",
  "fontStyle": "ITALIC",
  "hideCard": false,
  "iconSVG": "/static/media/icon.a55b701a2ae86aa2c6718ecb7b4083f0.svg",
  "isDeprecated": false,
  "isLoading": false,
  "isVisible": true,
  "key": "sb1e6ru07z",
  "leftColumn": 2,
  "maxDynamicHeight": 9000,
  "minDynamicHeight": 4,
  "minWidth": 450,
  "mobileBottomRow": 12,
  "mobileLeftColumn": 2,
  "mobileRightColumn": 18,
  "mobileTopRow": 8,
  "needsErrorInfo": false,
  "onCanvasUI": {
    "disableParentSelection": false,
    "focusBGCSSVar": "--on-canvas-ui-widget-focus",
    "focusColorCSSVar": "--on-canvas-ui-widget-selection",
    "selectionBGCSSVar": "--on-canvas-ui-widget-selection",
    "selectionColorCSSVar": "--on-canvas-ui-widget-focus"
  },
  "originalBottomRow": 13,
  "originalTopRow": 8,
  "overflow": "NONE",
  "parentColumnSpace": 6.1337890625,
  "parentId": "w4xfu87kwb",
  "parentRowSpace": 10,
  "renderMode": "CANVAS",
  "responsiveBehavior": "fill",
  "rightColumn": 64,
  "searchTags": [
    "typography",
    "paragraph",
    "label"
  ],
  "shouldTruncate": false,
  "tags": [
    "Suggested",
    "Content"
  ],
  "text": "Including themselves, how many guests in the party?",
  "textAlign": "LEFT",
  "textColor": "#231F20",
  "thumbnailSVG": "https://appcdn.appsmith.com/static/media/thumbnail.0c129b82c9b3e4cd4920563b289659ab.svg",
  "topRow": 8,
  "truncateButtonColor": "{{appsmith.theme.colors.primaryColor}}",
  "type": "TEXT_WIDGET",
  "version": 1,
  "widgetId": "un6ijy8ddd",
  "widgetName": "Text2"
}